cruscoplanets/COPYING
cruscoplanets/__init__.py
cruscoplanets/__main__.py
cruscoplanets/angles.py
cruscoplanets/aspects.py
cruscoplanets/chart_printer.py
cruscoplanets/charts.py
cruscoplanets/cmdline.py
cruscoplanets/dates.py
cruscoplanets/ephemeris.py
cruscoplanets/language_manager.py
cruscoplanets/location.py
cruscoplanets/person.py
cruscoplanets/planets_setter.py
cruscoplanets/svg_base.py
cruscoplanets/svg_settings.py
cruscoplanets/utils.py
cruscoplanets/c_libraries/vips-dev-w64-web-8.12.1/vips-dev-8.12/AUTHORS
cruscoplanets/c_libraries/vips-dev-w64-web-8.12.1/vips-dev-8.12/COPYING
cruscoplanets/c_libraries/vips-dev-w64-web-8.12.1/vips-dev-8.12/ChangeLog
cruscoplanets/c_libraries/vips-dev-w64-web-8.12.1/vips-dev-8.12/README.md
cruscoplanets/c_libraries/vips-dev-w64-web-8.12.1/vips-dev-8.12/versions.json
cruscoplanets/c_libraries/vips-dev-w64-web-8.12.1/vips-dev-8.12/bin/libaom.dll
cruscoplanets/c_libraries/vips-dev-w64-web-8.12.1/vips-dev-8.12/bin/libc++.dll
cruscoplanets/c_libraries/vips-dev-w64-web-8.12.1/vips-dev-8.12/bin/libcairo-2.dll
cruscoplanets/c_libraries/vips-dev-w64-web-8.12.1/vips-dev-8.12/bin/libcgif-0.dll
cruscoplanets/c_libraries/vips-dev-w64-web-8.12.1/vips-dev-8.12/bin/libexif-12.dll
cruscoplanets/c_libraries/vips-dev-w64-web-8.12.1/vips-dev-8.12/bin/libexpat-1.dll
cruscoplanets/c_libraries/vips-dev-w64-web-8.12.1/vips-dev-8.12/bin/libffi-8.dll
cruscoplanets/c_libraries/vips-dev-w64-web-8.12.1/vips-dev-8.12/bin/libfontconfig-1.dll
cruscoplanets/c_libraries/vips-dev-w64-web-8.12.1/vips-dev-8.12/bin/libfreetype-6.dll
cruscoplanets/c_libraries/vips-dev-w64-web-8.12.1/vips-dev-8.12/bin/libfribidi-0.dll
cruscoplanets/c_libraries/vips-dev-w64-web-8.12.1/vips-dev-8.12/bin/libgdk_pixbuf-2.0-0.dll
cruscoplanets/c_libraries/vips-dev-w64-web-8.12.1/vips-dev-8.12/bin/libgio-2.0-0.dll
cruscoplanets/c_libraries/vips-dev-w64-web-8.12.1/vips-dev-8.12/bin/libglib-2.0-0.dll
cruscoplanets/c_libraries/vips-dev-w64-web-8.12.1/vips-dev-8.12/bin/libgmodule-2.0-0.dll
cruscoplanets-0.3.1.dist-info/COPYING
cruscoplanets-0.3.1.dist-info/METADATA
cruscoplanets-0.3.1.dist-info/WHEEL
cruscoplanets-0.3.1.dist-info/entry_points.txt
cruscoplanets-0.3.1.dist-info/top_level.txt
cruscoplanets-0.3.1.dist-info/RECORD
