Metadata-Version: 2.1
Name: cruscoplanets
Version: 0.3.1
Summary: Graphic editor for Morpurgo's dialectic astrology
Home-page: https://gitlab.com/kikulacho92/cruscoplanets
Author: Emiliano Minerba
Author-email: emi.nerba@gmail.com
License: GPL
Platform: UNKNOWN
Requires-Dist: backports.zoneinfo[tzdata] (>=0.2.1)
Requires-Dist: lxml (>=4.7.1)
Requires-Dist: pyswisseph
Requires-Dist: pyvips (>=2.1.16)
Requires-Dist: timezonefinder
Requires-Dist: wheel
